COPYING
MANIFEST.in
README
VERSION
jsonchkstore
jsonchkstore.py
run_tests_with_coverage.sh
setup.py
test_jsonchkstore.py
jsonchkstore.egg-info/PKG-INFO
jsonchkstore.egg-info/SOURCES.txt
jsonchkstore.egg-info/dependency_links.txt
jsonchkstore.egg-info/requires.txt
jsonchkstore.egg-info/top_level.txt