Metadata-Version: 1.0
Name: jsonchkstore
Version: 0.99f5191420dd2749efb3a7c54a9280183983f485
Summary: Persistent directed acyclic graph storage with JSON and binary blobs using chkstore.
Home-page: https://bitbucket.org/nejucomo/jsonchkstore
Author: Nathan Wilcox
Author-email: nejucomo@gmail.com
License: GPLv3
Platform: UNKNOWN
